flask_bearychat/__init__.py
flask_bearychat/bearychat.py
Flask_BearyChat-0.1.1.dist-info/DESCRIPTION.rst
Flask_BearyChat-0.1.1.dist-info/METADATA
Flask_BearyChat-0.1.1.dist-info/metadata.json
Flask_BearyChat-0.1.1.dist-info/RECORD
Flask_BearyChat-0.1.1.dist-info/top_level.txt
Flask_BearyChat-0.1.1.dist-info/WHEEL
tests/__init__.py
