Metadata-Version: 2.0
Name: Flask-BearyChat
Version: 0.1.1
Summary: A Flask extension to help interact with BearyChat
Home-page: https://github.com/shonenada/flask-bearychat
Author: Yaoda Liu
Author-email: shonenada@gmail.com
License: MIT
Platform: UNKNOWN
Classifier: Framework :: Flask
Classifier: Programming Language :: Python
Classifier: Programming Language :: Python :: 2.7
Classifier: Programming Language :: Python :: 3.3
Classifier: Programming Language :: Python :: 3.4
Classifier: Programming Language :: Python :: Implementation :: PyPy
Classifier: Development Status :: 3 - Alpha
Classifier: Intended Audience :: Developers
Classifier: License :: OSI Approved :: MIT License
Classifier: Operating System :: OS Independent
Classifier: Topic :: Internet :: WWW/HTTP :: Dynamic Content
Classifier: Topic :: Software Development :: Libraries :: Python Modules
Requires-Dist: Flask
Requires-Dist: six
